func_profile_decor-0.1.7.dist-info/DESCRIPTION.rst
func_profile_decor-0.1.7.dist-info/METADATA
func_profile_decor-0.1.7.dist-info/RECORD
func_profile_decor-0.1.7.dist-info/WHEEL
func_profile_decor-0.1.7.dist-info/metadata.json
func_profile_decor-0.1.7.dist-info/top_level.txt
function_profile_decorator/__init__.py
function_profile_decorator/function_profile_decorator.py
