Metadata-Version: 2.0
Name: func-profile-decor
Version: 0.1.7
Summary: Profile a function using a simple decorator
Home-page: https://github.com/asanoryu/function_profile
Author: Vladislav Shumanov
Author-email: vl.shumanov@gmail.com
License: MIT
Platform: UNKNOWN
Classifier: License :: OSI Approved :: MIT License
Classifier: Programming Language :: Python :: 3
Classifier: Programming Language :: Python :: 3.7
Requires-Dist: memory-profiler
